pyphishtanklookup/__init__.py
pyphishtanklookup/api.py
pyphishtanklookup/py.typed
pyphishtanklookup-1.5.1.dist-info/METADATA
pyphishtanklookup-1.5.1.dist-info/WHEEL
pyphishtanklookup-1.5.1.dist-info/entry_points.txt
pyphishtanklookup-1.5.1.dist-info/licenses/LICENSE
pyphishtanklookup-1.5.1.dist-info/RECORD
