Metadata-Version: 2.4
Name: pyphishtanklookup
Version: 1.5.1
Summary: Python CLI and module for PhishtankLookup
License-Expression: BSD-3-Clause
License-File: LICENSE
Author: Raphaël Vinot
Author-email: raphael.vinot@circl.lu
Requires-Python: >=3.10
Classifier: Programming Language :: Python :: 3
Classifier: Programming Language :: Python :: 3.10
Classifier: Programming Language :: Python :: 3.11
Classifier: Programming Language :: Python :: 3.12
Classifier: Programming Language :: Python :: 3.13
Classifier: Programming Language :: Python :: 3.14
Provides-Extra: docs
Provides-Extra: lookyloo-example
Requires-Dist: Sphinx (>=8.2.3) ; (python_version >= "3.11") and (extra == "docs")
Requires-Dist: pylookyloo (>=1.34.0) ; extra == "lookyloo-example"
Requires-Dist: requests (>=2.32.5)
Project-URL: Documentation, https://pyphishtanklookup.readthedocs.io/
Project-URL: Repository, https://github.com/lookyloo/PyPhishtankLookup
Project-URL: issues, https://github.com/lookyloo/PyPhishtankLookup/issues
